droidflow/__init__.py
droidflow/domain.py
droidflow/model.py
droidflow/planer.py
droidflow/reasoner.py
droidflow/router.py
droidflow-0.0.2.2.dist-info/licenses/LICENSE
droidflow-0.0.2.2.dist-info/METADATA
droidflow-0.0.2.2.dist-info/WHEEL
droidflow-0.0.2.2.dist-info/top_level.txt
droidflow-0.0.2.2.dist-info/RECORD
