Metadata-Version: 2.4
Name: droidflow
Version: 0.0.2.2
Summary: A multi agent orchestrator library
Home-page: https://github.com/KaanSimsek/droidflow
Author: Kaan Simsek
Author-email: kaan.simsek01@gmail.com
Classifier: Programming Language :: Python :: 3
Classifier: License :: OSI Approved :: MIT License
Classifier: Operating System :: OS Independent
Requires-Python: >=3.7
License-File: LICENSE
Requires-Dist: google-generativeai>=0.5.0
Dynamic: author
Dynamic: author-email
Dynamic: classifier
Dynamic: description
Dynamic: description-content-type
Dynamic: home-page
Dynamic: license-file
Dynamic: requires-dist
Dynamic: requires-python
Dynamic: summary
